libs/__init__.py
libs/data.py
libs/image.py
libs/test.py
libs/web.py
libs_zip-0.0.4.dist-info/LICENSE
libs_zip-0.0.4.dist-info/METADATA
libs_zip-0.0.4.dist-info/WHEEL
libs_zip-0.0.4.dist-info/top_level.txt
libs_zip-0.0.4.dist-info/RECORD
